examples/basic-shipment.py
examples/batch.py
examples/estimate-shipping-prices.py
examples/filter-by-delivery-time.py
examples/get-rates-to-show-customer.py
examples/international-shipment.py
examples/multi_piece_shipment.py
examples/order-lineitem.py
examples/pickup.py
examples/purchase-fastest-service.py
examples/tracking.py
shippo/__init__.py
shippo/api_requestor.py
shippo/configuration.py
shippo/error.py
shippo/http_client.py
shippo/resource.py
shippo/version.py
modern_shippo-3.0.1.dist-info/METADATA
modern_shippo-3.0.1.dist-info/WHEEL
modern_shippo-3.0.1.dist-info/licenses/LICENSE
modern_shippo-3.0.1.dist-info/RECORD
