Metadata-Version: 2.1
Name: modern-shippo
Version: 3.0.1
Summary: Shipping API Python library (USPS, FedEx, UPS and more)
Project-URL: Homepage, https://github.com/prosehair/modern-shippo-python-client
Project-URL: Bug Tracker, https://github.com/prosehair/modern-shippo-python-client/issues
Author-email: Nicolas Mussat <nicolas@prose.com>, Shippo <support@goshippo.com>, Eyoel Asfaw <eyoela@gmail.com>, Subhi Beidas <subhi@goshippo.com>, Matthieu Nowicki <matthieu@goshippo.com>, Steve Byerly <steven.j.byerly@gmail.com>, Malcolm Rebughini <malcolm@goshippo.com>, Matthew Hwang <mhwang@goshippo.com>
Maintainer-email: Nicolas Mussat <nicolas@prose.com>
License-Expression: MIT
License-File: LICENSE
Classifier: Development Status :: 5 - Production/Stable
Classifier: Intended Audience :: Developers
Classifier: License :: OSI Approved :: MIT License
Classifier: Operating System :: OS Independent
Classifier: Programming Language :: Python
Classifier: Programming Language :: Python :: 3 :: Only
Classifier: Programming Language :: Python :: 3.10
Classifier: Programming Language :: Python :: 3.11
Classifier: Programming Language :: Python :: Implementation :: PyPy
Classifier: Topic :: Software Development :: Libraries :: Python Modules
Requires-Python: >=3.10
Requires-Dist: requests>=0.9.0
